microdatasets/__init__.py
microdatasets/__main__.py
microdatasets/version.py
microdatasets/assets/dsprites_ndarray_co1sh3sc6or40x32y32_64x64.npz
microdatasets/dsprites/__init__.py
microdatasets/dsprites/dsprites.py
microdatasets/dsprites/shape_generator.py
microdatasets-0.0.1.dist-info/LICENSE
microdatasets-0.0.1.dist-info/METADATA
microdatasets-0.0.1.dist-info/WHEEL
microdatasets-0.0.1.dist-info/top_level.txt
microdatasets-0.0.1.dist-info/RECORD
