Metadata-Version: 2.1
Name: microdatasets
Version: 0.0.1
Summary: Simple datasets for evaluating DL algorithms.
Home-page: https://github.com/FragileTech/microdatasets
Author: Guillem Duran Ballester
Author-email: guillem@fragile.tech
License: MIT
Keywords: Machine learning,artificial intelligence
Classifier: Development Status :: 3 - Alpha
Classifier: Intended Audience :: Developers
Classifier: License :: OSI Approved :: MIT License
Classifier: Programming Language :: Python :: 3.7
Classifier: Programming Language :: Python :: 3.8
Classifier: Programming Language :: Python :: 3.9
Classifier: Programming Language :: Python :: 3.10
Classifier: Topic :: Software Development :: Libraries
License-File: LICENSE
Requires-Dist: matplotlib
Requires-Dist: numpy
Requires-Dist: scipy
